CatMatcher/__init__.py
CatMatcher/match_configurator.py
CatMatcher/matcher.py
CatMatcher/shell_helper.py
catmatcher-0.1.1.dist-info/licenses/LICENSE
catmatcher-0.1.1.dist-info/METADATA
catmatcher-0.1.1.dist-info/WHEEL
catmatcher-0.1.1.dist-info/top_level.txt
catmatcher-0.1.1.dist-info/RECORD
