Metadata-Version: 2.4
Name: CatMatcher
Version: 0.1.1
Summary: A Python wrapper for the advanced crossmatching features of STILTS, offering more flexibility than the Topcat frontend and simplifying the process of using STILTS via the command line without the need for complex shell scripts.
Author-email: "A. Rottensteiner" <alena.rottensteiner@gmail.com>
License-Expression: MIT
Project-URL: Homepage, https://github.com/rottenstea/CatMatcher
Project-URL: Issues, https://github.com/rottenstea/CatMatcher/issues
Classifier: Programming Language :: Python :: 3
Classifier: Operating System :: OS Independent
Requires-Python: >=3.9
License-File: LICENSE
Dynamic: license-file
